FedInt/__init__.py
FedInt/config.py
FedInt/main.py
FedInt/models.py
FedInt/setup.py
FedInt/utils.py
fedin-1.0.1.dist-info/METADATA
fedin-1.0.1.dist-info/WHEEL
fedin-1.0.1.dist-info/top_level.txt
fedin-1.0.1.dist-info/RECORD
